MANIFEST.in
README.txt
setup.cfg
setup.py
rc/__init__.py
rc.theme.egg-info/PKG-INFO
rc.theme.egg-info/SOURCES.txt
rc.theme.egg-info/dependency_links.txt
rc.theme.egg-info/entry_points.txt
rc.theme.egg-info/namespace_packages.txt
rc.theme.egg-info/not-zip-safe
rc.theme.egg-info/paster_plugins.txt
rc.theme.egg-info/requires.txt
rc.theme.egg-info/top_level.txt
rc/theme/__init__.py
rc/theme/configure.zcml
rc/theme/profiles.zcml
rc/theme/setuphandlers.py
rc/theme/skins.zcml
rc/theme/tests.py
rc/theme/version.txt
rc/theme/browser/__init__.py
rc/theme/browser/configure.zcml
rc/theme/browser/interfaces.py
rc/theme/browser/viewlet.pt
rc/theme/browser/viewlets.py
rc/theme/browser/images/README.txt
rc/theme/browser/templates/footer.pt
rc/theme/browser/templates/logo.pt
rc/theme/browser/templates/searchbox.pt
rc/theme/profiles/default/cssregistry.xml
rc/theme/profiles/default/import_steps.xml
rc/theme/profiles/default/jsregistry.xml
rc/theme/profiles/default/metadata.xml
rc/theme/profiles/default/rc.theme_various.txt
rc/theme/profiles/default/skins.xml
rc/theme/profiles/default/viewlets.xml
rc/theme/skins/rc_theme_custom_images/CONTENT.txt
rc/theme/skins/rc_theme_custom_images/footer-bg.png
rc/theme/skins/rc_theme_custom_images/globalnav-bg.png
rc/theme/skins/rc_theme_custom_images/globalnav-selected-bg.png
rc/theme/skins/rc_theme_custom_images/page-actions-bg.png
rc/theme/skins/rc_theme_custom_images/portaltop-bg.png
rc/theme/skins/rc_theme_custom_images/portlet-calendar-days-bg.gif
rc/theme/skins/rc_theme_custom_images/portlet-header-bg.jpg
rc/theme/skins/rc_theme_custom_images/portlet-item-bg.gif
rc/theme/skins/rc_theme_custom_images/redaktionlabel.gif-alt
rc/theme/skins/rc_theme_custom_images/redaktionlabel.png
rc/theme/skins/rc_theme_custom_images/redaktionlabel.png--alt
rc/theme/skins/rc_theme_custom_images/suche.png
rc/theme/skins/rc_theme_custom_images/tools-bg-tinymce.png
rc/theme/skins/rc_theme_custom_images/tools-bg.png
rc/theme/skins/rc_theme_custom_images/topbuttons.png
rc/theme/skins/rc_theme_custom_templates/CONTENT.txt
rc/theme/skins/rc_theme_custom_templates/footer.pt
rc/theme/skins/rc_theme_styles/CONTENT.txt
rc/theme/skins/rc_theme_styles/redaktion.css.dtml