Metadata-Version: 1.0
Name: rc.theme
Version: 1.9.5.2
Summary: An installable theme for Plone 3.0
Home-page: http://svn.plone.org/svn/collective/
Author: Plone Collective
Author-email: product-developers@lists.plone.org
License: GPL
Keywords: web zope plone theme
Platform: UNKNOWN
Classifier: Framework :: Plone
Classifier: Programming Language :: Python
Classifier: Topic :: Software Development :: Libraries :: Python Modules
